installer/__init__.py
installer/pyinstaller_params.py
APASVO-0.0.6.dist-info/METADATA
APASVO-0.0.6.dist-info/DESCRIPTION.rst
APASVO-0.0.6.dist-info/top_level.txt
APASVO-0.0.6.dist-info/metadata.json
APASVO-0.0.6.dist-info/RECORD
APASVO-0.0.6.dist-info/WHEEL
apasvo/_version.py
apasvo/__init__.py
apasvo/utils/plotting.py
apasvo/utils/clt.py
apasvo/utils/futils.py
apasvo/utils/__init__.py
apasvo/utils/collections.py
apasvo/utils/parse.py
apasvo/utils/formats/__init__.py
apasvo/utils/formats/rawfile.py
apasvo/utils/formats/sacfile.py
apasvo/gui/__init__.py
apasvo/gui/trace_selector_dialog.py
apasvo/gui/mainwindow.py
apasvo/gui/views/ampadialog.py
apasvo/gui/views/navigationtoolbar.py
apasvo/gui/views/tsvwidget.py
apasvo/gui/views/loaddialog.py
apasvo/gui/views/__init__.py
apasvo/gui/views/takanamidialog.py
apasvo/gui/views/error.py
apasvo/gui/views/trace_selector_dialog.py
apasvo/gui/views/settingsdialog.py
apasvo/gui/views/staltadialog.py
apasvo/gui/views/save_events_dialog.py
apasvo/gui/views/playertoolbar.py
apasvo/gui/views/savedialog.py
apasvo/gui/views/svwidget.py
apasvo/gui/views/FilterDesing.py
apasvo/gui/views/mainwindow.py
apasvo/gui/views/aboutdialog.py
apasvo/gui/views/processingdialog.py
apasvo/gui/views/tracewindow.py
apasvo/gui/views/generated/ui_loaddialog.py
apasvo/gui/views/generated/ui_mainwindow.py
apasvo/gui/views/generated/__init__.py
apasvo/gui/views/generated/ui_savedialog.py
apasvo/gui/views/generated/qrc_strings.py
apasvo/gui/views/generated/qrc_icons.py
apasvo/gui/views/generated/ui_tracewindow.py
apasvo/gui/views/generated/ui_save_events_dialog.py
apasvo/gui/delegates/dsbdelegate.py
apasvo/gui/delegates/__init__.py
apasvo/gui/delegates/cbdelegate.py
apasvo/gui/models/filterlistmodel.py
apasvo/gui/models/__init__.py
apasvo/gui/models/pickingtask.py
apasvo/gui/models/eventcommands.py
apasvo/gui/models/eventlistmodel.py
apasvo/picking/takanami.py
apasvo/picking/envelope.py
apasvo/picking/__init__.py
apasvo/picking/ampa.py
apasvo/picking/stalta.py
apasvo/picking/eqgenerator.py
apasvo/picking/findpeaks.py
apasvo/picking/apasvotrace.py
tests/__init__.py
tests/tests_utils.py
