Metadata-Version: 2.0
Name: APASVO
Version: 0.0.6
Summary: A graphical tool to perform event detection/picking in seismic traces.
Home-page: https://github.com/jemromerol/apasvo
Author: Jose Emilio Romero Lopez
Author-email: jemromerol@gmail.com
License: GPL
Download-URL: https://github.com/jemromerol/apasvo/releases/tag/v0.0.6
Keywords: seismology,earthquakes,seismogram,picking,picker,P-phase arrival,STA-LTA,AMPA,autoregressive method,Takanami,characteristic function
Platform: UNKNOWN
Classifier: Development Status :: 3 - Alpha
Classifier: Intended Audience :: Science/Research
Classifier: License :: OSI Approved :: GNU General Public License v3 (GPLv3)
Classifier: Programming Language :: Python
Classifier: Topic :: Scientific/Engineering
Requires-Dist: PySide (==1.2.2)
Requires-Dist: SQLAlchemy (==0.9.9)
Requires-Dist: argparse (==1.2.1)
Requires-Dist: backports.ssl-match-hostname (==3.4.0.2)
Requires-Dist: coverage (==3.7.1)
Requires-Dist: future (==0.14.3)
Requires-Dist: lxml (==3.4.2)
Requires-Dist: matplotlib (==1.3.1)
Requires-Dist: mock (==1.0.1)
Requires-Dist: nose (==1.3.1)
Requires-Dist: numpy (==1.8.1)
Requires-Dist: obspy (==0.10.1)
Requires-Dist: pyparsing (==2.0.2)
Requires-Dist: python-dateutil (==2.2)
Requires-Dist: pytz (==2014.10)
Requires-Dist: scipy (==0.13.3)
Requires-Dist: six (==1.6.1)
Requires-Dist: tornado (==3.2)
Requires-Dist: wheel (==0.24.0)
Requires-Dist: wsgiref (==0.1.2)
